dpmm/__init__.py
dpmm/models/__init__.py
dpmm/models/aim.py
dpmm/models/base/__init__.py
dpmm/models/base/base.py
dpmm/models/base/compression.py
dpmm/models/base/graphical.py
dpmm/models/base/matrix.py
dpmm/models/base/mbi/README.md
dpmm/models/base/mbi/__init__.py
dpmm/models/base/mbi/callbacks.py
dpmm/models/base/mbi/clique_vector.py
dpmm/models/base/mbi/dataset.py
dpmm/models/base/mbi/domain.py
dpmm/models/base/mbi/factor.py
dpmm/models/base/mbi/graphical_model.py
dpmm/models/base/mbi/inference.py
dpmm/models/base/mbi/junction_tree.py
dpmm/models/base/mechanisms/__init__.py
dpmm/models/base/mechanisms/cdp2adp.py
dpmm/models/base/mechanisms/mechanism.py
dpmm/models/base/memory.py
dpmm/models/base/utils.py
dpmm/models/mst.py
dpmm/models/priv_bayes.py
dpmm/pipelines/__init__.py
dpmm/pipelines/aim.py
dpmm/pipelines/base.py
dpmm/pipelines/mst.py
dpmm/pipelines/priv_bayes.py
dpmm/processing/__init__.py
dpmm/processing/binners.py
dpmm/processing/table_binner.py
dpmm/processing/utils.py
dpmm/utils.py
dpmm-0.1.9.dist-info/LICENSE
dpmm-0.1.9.dist-info/METADATA
dpmm-0.1.9.dist-info/WHEEL
dpmm-0.1.9.dist-info/RECORD
