Metadata-Version: 2.3
Name: dpmm
Version: 0.1.9
Summary: dpmm: a library for synthetic tabular data generation with rich functionality and end-to-end Differential Privacy guarantees
License: Apache-2.0
Keywords: machine-learning,tabular-data,differential-privacy,synthetic-data
Author: Sofiane Mahiou, Georgi Ganev
Author-email: sofiane.mahiou@sas.com
Maintainer: Sofiane Mahiou
Maintainer-email: sofiane.mahiou@sas.com
Requires-Python: >=3.10,<3.12
Classifier: License :: OSI Approved :: Apache Software License
Classifier: Programming Language :: Python :: 3
Classifier: Programming Language :: Python :: 3.10
Classifier: Programming Language :: Python :: 3.11
Requires-Dist: disjoint-set (==0.7.4)
Requires-Dist: networkx (<3.0)
Requires-Dist: numpy (==1.26.4)
Requires-Dist: opendp (==0.12.1)
Requires-Dist: pandas (==2.1.0)
Requires-Dist: scikit-learn (==1.5.0)
Requires-Dist: scipy (>=1.15.2,<2.0.0)
Requires-Dist: tqdm (>=4.67.1,<5.0.0)
Project-URL: Homepage, https://github.com/sassoftware/dpmm
Project-URL: arxiv, https://arxiv.org/abs/2506.00322
